tendril/__init__.py
tendril/utils/__init__.py
tendril/utils/files/__init__.py
tendril/utils/files/gschem.py
tendril/utils/files/libreoffice.py
tendril/utils/files/markdown.py
tendril/utils/files/pdf.py
tendril/utils/files/yml.py
tendril_utils_files-0.1.1.dist-info/DESCRIPTION.rst
tendril_utils_files-0.1.1.dist-info/METADATA
tendril_utils_files-0.1.1.dist-info/RECORD
tendril_utils_files-0.1.1.dist-info/WHEEL
tendril_utils_files-0.1.1.dist-info/metadata.json
tendril_utils_files-0.1.1.dist-info/top_level.txt
