Metadata-Version: 2.0
Name: tendril-utils-files
Version: 0.1.1
Summary: File manipulation utilities for tendril
Home-page: https://github.com/chintal/tendril-utils-files
Author: Chintalagiri Shashank
Author-email: shashank@chintal.in
License: AGPLv3
Keywords: tendril
Platform: UNKNOWN
Classifier: Development Status :: 4 - Beta
Classifier: Natural Language :: English
Classifier: Programming Language :: Python
Requires-Dist: PyPDF2
Requires-Dist: mistune
Requires-Dist: pyyaml
Requires-Dist: six
Requires-Dist: tendril-dox-wallet (>=0.1.1)
Requires-Dist: tendril-utils-core (>=0.1.4)
